selenium_recaptcha/__init__.py
selenium_recaptcha/components.py
selenium_recaptcha-1.0.7.dist-info/METADATA
selenium_recaptcha-1.0.7.dist-info/WHEEL
selenium_recaptcha-1.0.7.dist-info/top_level.txt
selenium_recaptcha-1.0.7.dist-info/RECORD
