Metadata-Version: 2.1
Name: selenium-recaptcha
Version: 1.0.7
Summary: reCaptcha v2 solver for selenium
Home-page: UNKNOWN
Author: S M Shahriar Zarir
Author-email: <shahriarzariradvance@gmail.com>
License: UNKNOWN
Keywords: python,reCaptcha,bot,selenium,selenium recaptcha solver
Platform: UNKNOWN
Classifier: Development Status :: 1 - Planning
Classifier: Intended Audience :: Developers
Classifier: Programming Language :: Python :: 3
Classifier: Operating System :: Unix
Classifier: Operating System :: MacOS :: MacOS X
Classifier: Operating System :: Microsoft :: Windows
Requires-Dist: requests
Requires-Dist: ffmpeg-downloader
Requires-Dist: openai-whisper
Requires-Dist: selenium
